similarius/__init__.py
similarius/py.typing
similarius/similarius.py
similarius-0.0.2.dist-info/LICENSE
similarius-0.0.2.dist-info/METADATA
similarius-0.0.2.dist-info/WHEEL
similarius-0.0.2.dist-info/entry_points.txt
similarius-0.0.2.dist-info/RECORD
