Metadata-Version: 2.3
Name: similarius
Version: 0.0.2
Summary: Compare web page and evaluate the level of similarity.
License: BSD-2-Clause
Keywords: web similarity,web comparaison
Author: David Cruciani
Author-email: david.cruciani@circl.lu
Maintainer: Alexandre Dulaunoy
Maintainer-email: a@foo.be
Requires-Python: >=3.8,<4.0
Classifier: License :: OSI Approved :: BSD License
Classifier: Programming Language :: Python :: 3
Classifier: Programming Language :: Python :: 3.8
Classifier: Programming Language :: Python :: 3.9
Classifier: Programming Language :: Python :: 3.10
Classifier: Programming Language :: Python :: 3.11
Classifier: Programming Language :: Python :: 3.12
Classifier: Programming Language :: Python :: 3.13
Requires-Dist: beautifulsoup4 (>=4.11.1,<5.0.0)
Requires-Dist: lxml (>=4.9.2,<6.0.0)
Requires-Dist: nltk (>=3.8.1,<4.0.0)
Requires-Dist: requests (>=2.28.2,<3.0.0)
Requires-Dist: scikit-learn (>=1.2.0,<2.0.0)
Project-URL: Repository, https://github.com/ail-project/Similarius
